migropy/__init__.py
migropy/cli.py
migropy/commands/__init__.py
migropy/commands/command.py
migropy/configuration_parser.py
migropy/core/__init__.py
migropy/core/config.py
migropy/core/logger.py
migropy/databases/__init__.py
migropy/databases/base_adapter.py
migropy/databases/commons.py
migropy/databases/my_sql.py
migropy/databases/postgres.py
migropy/databases/services.py
migropy/migration_engine.py
migropy/templates/migropy.ini
migropy-0.4.1.dist-info/LICENSE
migropy-0.4.1.dist-info/METADATA
migropy-0.4.1.dist-info/WHEEL
migropy-0.4.1.dist-info/entry_points.txt
migropy-0.4.1.dist-info/RECORD
