Metadata-Version: 2.3
Name: migropy
Version: 0.4.1
Summary: Lightweight and extensible Python library for managing database migrations
License: MIT
Keywords: database,migrations,postgresql,mysql,sql,cli
Author: fredimatteo
Author-email: matteofredi.developer@gmail.com
Requires-Python: >=3.10.0,<4.0.0
Classifier: Development Status :: 4 - Beta
Classifier: Intended Audience :: Developers
Classifier: License :: OSI Approved :: MIT License
Classifier: Programming Language :: Python :: 3
Classifier: Programming Language :: Python :: 3.10
Classifier: Programming Language :: Python :: 3.11
Classifier: Programming Language :: Python :: 3.12
Classifier: Programming Language :: Python :: 3.13
Classifier: Topic :: Software Development :: Libraries :: Python Modules
Classifier: Topic :: Database
Requires-Dist: mysql-connector-python (>=9.2.0,<10.0.0)
Requires-Dist: psycopg (>=3.2.6,<4.0.0)
Requires-Dist: pytest-mock (>=3.14.0,<4.0.0)
Project-URL: Homepage, https://github.com/fredimatteo/migropy/blob/develop/README.md
Project-URL: Repository, https://github.com/fredimatteo/migropy.git
